cyberette-0.1.2.dist-info/licenses/LICENSE
cyberette_sdk/__init__.py
cyberette_sdk/client.py
cyberette_sdk/errors.py
cyberette_sdk/models.py
cyberette_sdk/utils.py
cyberette-0.1.2.dist-info/METADATA
cyberette-0.1.2.dist-info/WHEEL
cyberette-0.1.2.dist-info/top_level.txt
cyberette-0.1.2.dist-info/RECORD
