Metadata-Version: 2.4
Name: cyberette
Version: 0.1.2
Summary: Python SDK for Your Detection API
Author: Stefan Saveski
License-Expression: MIT
License-File: LICENSE
Requires-Dist: aiohttp
Requires-Dist: moviepy==2.1.2
Requires-Dist: imageio-ffmpeg
Requires-Dist: pydantic
Provides-Extra: dev
Requires-Dist: pytest; extra == "dev"
Requires-Dist: pytest-asyncio; extra == "dev"
Dynamic: license-file
